[1,["35SPTvYF5IN5wpMqkbxRzK@6c48a","4dI/MbXx1HzKJm/GwWUj0a@6c48a","63VyUpr3xH27YXZFdSpcUC@6c48a","73dyaxvPtJWpbzmO8+THMs@6c48a","83S3UbPcpM86aUDqftSs03@6c48a","e3LIxQyCZIPq7SrmNsc6o8@6c48a"],["_textureSource"],["cc.SpriteFrame"],0,[[[{"name":"008","rect":{"x":0,"y":0,"width":64,"height":64},"offset":{"x":0,"y":0},"originalSize":{"width":64,"height":64},"rotated":false,"capInsets":[0,0,0,0],"vertices":{"rawPosition":[-32,-32,0,32,-32,0,-32,32,0,32,32,0],"indexes":[0,1,2,2,1,3],"uv":[0,64,64,64,0,0,64,0],"nuv":[0,0,1,0,0,1,1,1],"minPos":{"x":-32,"y":-32,"z":0},"maxPos":{"x":32,"y":32,"z":0}},"packable":true,"pixelsToUnit":100,"pivot":{"x":0.5,"y":0.5},"meshType":0}],[0],0,[0],[0],[0]],[[{"name":"011","rect":{"x":0,"y":0,"width":64,"height":64},"offset":{"x":0,"y":0},"originalSize":{"width":64,"height":64},"rotated":false,"capInsets":[0,0,0,0],"vertices":{"rawPosition":[-32,-32,0,32,-32,0,-32,32,0,32,32,0],"indexes":[0,1,2,2,1,3],"uv":[0,64,64,64,0,0,64,0],"nuv":[0,0,1,0,0,1,1,1],"minPos":{"x":-32,"y":-32,"z":0},"maxPos":{"x":32,"y":32,"z":0}},"packable":true,"pixelsToUnit":100,"pivot":{"x":0.5,"y":0.5},"meshType":0}],[0],0,[0],[0],[1]],[[{"name":"009","rect":{"x":0,"y":0,"width":64,"height":64},"offset":{"x":0,"y":0},"originalSize":{"width":64,"height":64},"rotated":false,"capInsets":[0,0,0,0],"vertices":{"rawPosition":[-32,-32,0,32,-32,0,-32,32,0,32,32,0],"indexes":[0,1,2,2,1,3],"uv":[0,64,64,64,0,0,64,0],"nuv":[0,0,1,0,0,1,1,1],"minPos":{"x":-32,"y":-32,"z":0},"maxPos":{"x":32,"y":32,"z":0}},"packable":true,"pixelsToUnit":100,"pivot":{"x":0.5,"y":0.5},"meshType":0}],[0],0,[0],[0],[2]],[[{"name":"012","rect":{"x":0,"y":0,"width":64,"height":64},"offset":{"x":0,"y":0},"originalSize":{"width":64,"height":64},"rotated":false,"capInsets":[0,0,0,0],"vertices":{"rawPosition":[-32,-32,0,32,-32,0,-32,32,0,32,32,0],"indexes":[0,1,2,2,1,3],"uv":[0,64,64,64,0,0,64,0],"nuv":[0,0,1,0,0,1,1,1],"minPos":{"x":-32,"y":-32,"z":0},"maxPos":{"x":32,"y":32,"z":0}},"packable":true,"pixelsToUnit":100,"pivot":{"x":0.5,"y":0.5},"meshType":0}],[0],0,[0],[0],[3]],[[{"name":"013","rect":{"x":0,"y":0,"width":64,"height":64},"offset":{"x":0,"y":0},"originalSize":{"width":64,"height":64},"rotated":false,"capInsets":[0,0,0,0],"vertices":{"rawPosition":[-32,-32,0,32,-32,0,-32,32,0,32,32,0],"indexes":[0,1,2,2,1,3],"uv":[0,64,64,64,0,0,64,0],"nuv":[0,0,1,0,0,1,1,1],"minPos":{"x":-32,"y":-32,"z":0},"maxPos":{"x":32,"y":32,"z":0}},"packable":true,"pixelsToUnit":100,"pivot":{"x":0.5,"y":0.5},"meshType":0}],[0],0,[0],[0],[4]],[[{"name":"010","rect":{"x":0,"y":0,"width":64,"height":64},"offset":{"x":0,"y":0},"originalSize":{"width":64,"height":64},"rotated":false,"capInsets":[0,0,0,0],"vertices":{"rawPosition":[-32,-32,0,32,-32,0,-32,32,0,32,32,0],"indexes":[0,1,2,2,1,3],"uv":[0,64,64,64,0,0,64,0],"nuv":[0,0,1,0,0,1,1,1],"minPos":{"x":-32,"y":-32,"z":0},"maxPos":{"x":32,"y":32,"z":0}},"packable":true,"pixelsToUnit":100,"pivot":{"x":0.5,"y":0.5},"meshType":0}],[0],0,[0],[0],[5]]]]
