[1,["06DLgj6ytHJ7PDhGu1gEhq@6c48a","2eUVw4Hz1LFJfPgFWfa9Ax@6c48a","73t695O29NEanEAwGoQwpn@6c48a","a8tA89VLtFs55R9UjZz5ba@6c48a","a8vRnrF4dFPraADwJQwkq4@6c48a","ab74pljH1F1YuUSI94Lw5n@6c48a","d7fQ8vNoFDcIKg13Ap0ye2@6c48a","dbAc22celLhaeNZ0U332BT@6c48a"],["_textureSource"],["cc.SpriteFrame"],0,[[[{"name":"23","rect":{"x":0,"y":0,"width":32,"height":64},"offset":{"x":0,"y":0},"originalSize":{"width":32,"height":64},"rotated":false,"capInsets":[0,0,0,0],"vertices":{"rawPosition":[-16,-32,0,16,-32,0,-16,32,0,16,32,0],"indexes":[0,1,2,2,1,3],"uv":[0,64,32,64,0,0,32,0],"nuv":[0,0,1,0,0,1,1,1],"minPos":{"x":-16,"y":-32,"z":0},"maxPos":{"x":16,"y":32,"z":0}},"packable":true,"pixelsToUnit":100,"pivot":{"x":0.5,"y":0.5},"meshType":0}],[0],0,[0],[0],[0]],[[{"name":"17","rect":{"x":0,"y":0,"width":32,"height":64},"offset":{"x":0,"y":0},"originalSize":{"width":32,"height":64},"rotated":false,"capInsets":[0,0,0,0],"vertices":{"rawPosition":[-16,-32,0,16,-32,0,-16,32,0,16,32,0],"indexes":[0,1,2,2,1,3],"uv":[0,64,32,64,0,0,32,0],"nuv":[0,0,1,0,0,1,1,1],"minPos":{"x":-16,"y":-32,"z":0},"maxPos":{"x":16,"y":32,"z":0}},"packable":true,"pixelsToUnit":100,"pivot":{"x":0.5,"y":0.5},"meshType":0}],[0],0,[0],[0],[1]],[[{"name":"19","rect":{"x":0,"y":0,"width":32,"height":64},"offset":{"x":0,"y":0},"originalSize":{"width":32,"height":64},"rotated":false,"capInsets":[0,0,0,0],"vertices":{"rawPosition":[-16,-32,0,16,-32,0,-16,32,0,16,32,0],"indexes":[0,1,2,2,1,3],"uv":[0,64,32,64,0,0,32,0],"nuv":[0,0,1,0,0,1,1,1],"minPos":{"x":-16,"y":-32,"z":0},"maxPos":{"x":16,"y":32,"z":0}},"packable":true,"pixelsToUnit":100,"pivot":{"x":0.5,"y":0.5},"meshType":0}],[0],0,[0],[0],[2]],[[{"name":"24","rect":{"x":0,"y":0,"width":32,"height":64},"offset":{"x":0,"y":0},"originalSize":{"width":32,"height":64},"rotated":false,"capInsets":[0,0,0,0],"vertices":{"rawPosition":[-16,-32,0,16,-32,0,-16,32,0,16,32,0],"indexes":[0,1,2,2,1,3],"uv":[0,64,32,64,0,0,32,0],"nuv":[0,0,1,0,0,1,1,1],"minPos":{"x":-16,"y":-32,"z":0},"maxPos":{"x":16,"y":32,"z":0}},"packable":true,"pixelsToUnit":100,"pivot":{"x":0.5,"y":0.5},"meshType":0}],[0],0,[0],[0],[3]],[[{"name":"18","rect":{"x":0,"y":0,"width":32,"height":64},"offset":{"x":0,"y":0},"originalSize":{"width":32,"height":64},"rotated":false,"capInsets":[0,0,0,0],"vertices":{"rawPosition":[-16,-32,0,16,-32,0,-16,32,0,16,32,0],"indexes":[0,1,2,2,1,3],"uv":[0,64,32,64,0,0,32,0],"nuv":[0,0,1,0,0,1,1,1],"minPos":{"x":-16,"y":-32,"z":0},"maxPos":{"x":16,"y":32,"z":0}},"packable":true,"pixelsToUnit":100,"pivot":{"x":0.5,"y":0.5},"meshType":0}],[0],0,[0],[0],[4]],[[{"name":"21","rect":{"x":0,"y":0,"width":32,"height":64},"offset":{"x":0,"y":0},"originalSize":{"width":32,"height":64},"rotated":false,"capInsets":[0,0,0,0],"vertices":{"rawPosition":[-16,-32,0,16,-32,0,-16,32,0,16,32,0],"indexes":[0,1,2,2,1,3],"uv":[0,64,32,64,0,0,32,0],"nuv":[0,0,1,0,0,1,1,1],"minPos":{"x":-16,"y":-32,"z":0},"maxPos":{"x":16,"y":32,"z":0}},"packable":true,"pixelsToUnit":100,"pivot":{"x":0.5,"y":0.5},"meshType":0}],[0],0,[0],[0],[5]],[[{"name":"22","rect":{"x":0,"y":0,"width":32,"height":64},"offset":{"x":0,"y":0},"originalSize":{"width":32,"height":64},"rotated":false,"capInsets":[0,0,0,0],"vertices":{"rawPosition":[-16,-32,0,16,-32,0,-16,32,0,16,32,0],"indexes":[0,1,2,2,1,3],"uv":[0,64,32,64,0,0,32,0],"nuv":[0,0,1,0,0,1,1,1],"minPos":{"x":-16,"y":-32,"z":0},"maxPos":{"x":16,"y":32,"z":0}},"packable":true,"pixelsToUnit":100,"pivot":{"x":0.5,"y":0.5},"meshType":0}],[0],0,[0],[0],[6]],[[{"name":"20","rect":{"x":0,"y":0,"width":32,"height":64},"offset":{"x":0,"y":0},"originalSize":{"width":32,"height":64},"rotated":false,"capInsets":[0,0,0,0],"vertices":{"rawPosition":[-16,-32,0,16,-32,0,-16,32,0,16,32,0],"indexes":[0,1,2,2,1,3],"uv":[0,64,32,64,0,0,32,0],"nuv":[0,0,1,0,0,1,1,1],"minPos":{"x":-16,"y":-32,"z":0},"maxPos":{"x":16,"y":32,"z":0}},"packable":true,"pixelsToUnit":100,"pivot":{"x":0.5,"y":0.5},"meshType":0}],[0],0,[0],[0],[7]]]]
